LICENSE
MANIFEST.in
README.md
setup.py
miniature/__init__.py
miniature/__init__.pyc
miniature/context_processors.py
miniature/admin/__init__.py
miniature/admin/options.py
miniature/admin/templatetags/__init__.py
miniature/admin/templatetags/range.py
miniature/api/__init__.py
miniature/api/authorization.py
miniature/api/monkey.py
miniature/api/utils.py
miniature/models/.fields.py.swp
miniature/models/.mixins.py.swp
miniature/models/__init__.py
miniature/models/__init__.pyc
miniature/models/fields.py
miniature/models/fields.pyc
miniature/models/mixins.py
miniature/models/mixins.pyc
miniature/models/utils.py
miniature/models/utils.pyc
miniature_ironman.egg-info/PKG-INFO
miniature_ironman.egg-info/SOURCES.txt
miniature_ironman.egg-info/dependency_links.txt
miniature_ironman.egg-info/not-zip-safe
miniature_ironman.egg-info/requires.txt
miniature_ironman.egg-info/top_level.txt