Metadata-Version: 1.1
Name: miniature-ironman
Version: 0.0.4
Summary: My code snippets set for django
Home-page: https://github.com/ir4y/miniature-ironman
Author: Ilya Beda
Author-email: ir4y.ix@gmail.com
License: UNKNOWN
Platform: UNKNOWN
Classifier: Development Status :: 4 - Beta
Classifier: Environment :: Web Environment
Classifier: Framework :: Django
Classifier: Intended Audience :: Developers
Classifier: License :: OSI Approved :: BSD License
Classifier: Operating System :: OS Independent
Classifier: Programming Language :: Python
